<annotation>
	<folder>out</folder>
	<filename>00173.jpg</filename>
	<path>C:\Users\Administrator\Downloads\out\00173.jpg</path>
	<source>
		<database>Unknown</database>
	</source>
	<size>
		<width>1111</width>
		<height>761</height>
		<depth>3</depth>
	</size>
	<segmented>0</segmented>
	<object>
		<name>heavy truck</name>
		<pose>Unspecified</pose>
		<truncated>0</truncated>
		<difficult>0</difficult>
		<bndbox>
			<xmin>230</xmin>
			<ymin>81</ymin>
			<xmax>780</xmax>
			<ymax>681</ymax>
		</bndbox>
	</object>
</annotation>
