<annotation>
	<folder>out</folder>
	<filename>00339.jpg</filename>
	<path>C:\Users\Administrator\Downloads\out\00339.jpg</path>
	<source>
		<database>Unknown</database>
	</source>
	<size>
		<width>1034</width>
		<height>690</height>
		<depth>3</depth>
	</size>
	<segmented>0</segmented>
	<object>
		<name>jeep</name>
		<pose>Unspecified</pose>
		<truncated>0</truncated>
		<difficult>0</difficult>
		<bndbox>
			<xmin>41</xmin>
			<ymin>66</ymin>
			<xmax>985</xmax>
			<ymax>655</ymax>
		</bndbox>
	</object>
</annotation>
