<annotation>
	<folder>out</folder>
	<filename>00418.jpg</filename>
	<path>C:\Users\Administrator\Downloads\out\00418.jpg</path>
	<source>
		<database>Unknown</database>
	</source>
	<size>
		<width>1154</width>
		<height>736</height>
		<depth>3</depth>
	</size>
	<segmented>0</segmented>
	<object>
		<name>heavy truck</name>
		<pose>Unspecified</pose>
		<truncated>0</truncated>
		<difficult>0</difficult>
		<bndbox>
			<xmin>76</xmin>
			<ymin>76</ymin>
			<xmax>1127</xmax>
			<ymax>690</ymax>
		</bndbox>
	</object>
</annotation>
