<annotation>
	<folder>out</folder>
	<filename>00438.jpg</filename>
	<path>C:\Users\Administrator\Downloads\out\00438.jpg</path>
	<source>
		<database>Unknown</database>
	</source>
	<size>
		<width>643</width>
		<height>438</height>
		<depth>3</depth>
	</size>
	<segmented>0</segmented>
	<object>
		<name>taxi</name>
		<pose>Unspecified</pose>
		<truncated>0</truncated>
		<difficult>0</difficult>
		<bndbox>
			<xmin>62</xmin>
			<ymin>103</ymin>
			<xmax>598</xmax>
			<ymax>357</ymax>
		</bndbox>
	</object>
</annotation>
