<annotation>
	<folder>out</folder>
	<filename>00540.jpg</filename>
	<path>C:\Users\Administrator\Downloads\out\00540.jpg</path>
	<source>
		<database>Unknown</database>
	</source>
	<size>
		<width>1251</width>
		<height>809</height>
		<depth>3</depth>
	</size>
	<segmented>0</segmented>
	<object>
		<name>truck</name>
		<pose>Unspecified</pose>
		<truncated>0</truncated>
		<difficult>0</difficult>
		<bndbox>
			<xmin>443</xmin>
			<ymin>179</ymin>
			<xmax>899</xmax>
			<ymax>766</ymax>
		</bndbox>
	</object>
</annotation>
